epi2melabs_wfpage/__init__.py
epi2melabs_wfpage/_version.py
epi2melabs_wfpage/config.py
epi2melabs_wfpage/handlers.py
epi2melabs_wfpage/labextension/package.json
epi2melabs_wfpage/labextension/schemas/@epi2melabs/epi2melabs-wfpage/package.json.orig
epi2melabs_wfpage/labextension/schemas/@epi2melabs/epi2melabs-wfpage/plugin.json
epi2melabs_wfpage/labextension/static/131.b427a70c264415de668c.js
epi2melabs_wfpage/labextension/static/246.0c8763e661362df19caf.js
epi2melabs_wfpage/labextension/static/328.82e57d58db283aec3c7a.js
epi2melabs_wfpage/labextension/static/382.dbcfc2d9d3c1c56b2b1c.js
epi2melabs_wfpage/labextension/static/394.5e604a7fdfa73e47513c.js
epi2melabs_wfpage/labextension/static/402.579d5264b01792c264dc.js
epi2melabs_wfpage/labextension/static/402.579d5264b01792c264dc.js.LICENSE.txt
epi2melabs_wfpage/labextension/static/442.6d0d188d2b7aa9f4b0a6.js
epi2melabs_wfpage/labextension/static/442.6d0d188d2b7aa9f4b0a6.js.LICENSE.txt
epi2melabs_wfpage/labextension/static/486.13f098a446edf7385205.js
epi2melabs_wfpage/labextension/static/486.13f098a446edf7385205.js.LICENSE.txt
epi2melabs_wfpage/labextension/static/55.978e8f477728f093b9e4.js
epi2melabs_wfpage/labextension/static/581.8853988b558bf4474ac8.js
epi2melabs_wfpage/labextension/static/581.8853988b558bf4474ac8.js.LICENSE.txt
epi2melabs_wfpage/labextension/static/612.7ca668d53625da2603a7.js
epi2melabs_wfpage/labextension/static/612.7ca668d53625da2603a7.js.LICENSE.txt
epi2melabs_wfpage/labextension/static/634.e0fcf30aaf021014c34a.js
epi2melabs_wfpage/labextension/static/700.f59cfffdfc287ef49406.js
epi2melabs_wfpage/labextension/static/71.bcf3805e95818a336bee.js
epi2melabs_wfpage/labextension/static/719.8d19998466b9b7d9200c.js
epi2melabs_wfpage/labextension/static/719.8d19998466b9b7d9200c.js.LICENSE.txt
epi2melabs_wfpage/labextension/static/747.b466b27f35b1af39d181.js
epi2melabs_wfpage/labextension/static/762.bb8c9a834931e955b1f8.js
epi2melabs_wfpage/labextension/static/762.bb8c9a834931e955b1f8.js.LICENSE.txt
epi2melabs_wfpage-0.2.9.dist-info/LICENSE
epi2melabs_wfpage-0.2.9.dist-info/METADATA
epi2melabs_wfpage-0.2.9.dist-info/WHEEL
epi2melabs_wfpage-0.2.9.dist-info/top_level.txt
epi2melabs_wfpage-0.2.9.dist-info/RECORD
