Metadata-Version: 2.1
Name: epi2melabs-wfpage
Version: 0.2.9
Summary: A jupyterlab launcher for Nextflow workflows
Home-page: https://github.com/epi2me-labs/epi2melabs-wfpage
Author: epi2melabs
License: BSD-3-Clause
Keywords: Jupyter,JupyterLab,JupyterLab3
Platform: Linux
Platform: Mac OS X
Platform: Windows
Classifier: License :: OSI Approved :: BSD License
Classifier: Programming Language :: Python
Classifier: Programming Language :: Python :: 3.8
Classifier: Programming Language :: Python :: 3.9
Classifier: Programming Language :: Python :: 3.10
Classifier: Framework :: Jupyter
Classifier: Framework :: Jupyter :: JupyterLab
Classifier: Framework :: Jupyter :: JupyterLab :: 3
Classifier: Framework :: Jupyter :: JupyterLab :: Extensions
Classifier: Framework :: Jupyter :: JupyterLab :: Extensions :: Prebuilt
Requires-Python: >=3.8
License-File: LICENSE
Requires-Dist: jupyter-server (<2,>=1.6)
Requires-Dist: jupyter-packaging
Requires-Dist: epi2melabs
